blobjugglerpy/__init__.py
blobjugglerpy/__main__.py
blobjugglerpy/cli.py
blobjugglerpy/constants.py
blobjugglerpy/csv_export.py
blobjugglerpy/flatteners.py
blobjugglerpy/rosbag_utils.py
blobjugglerpy/utils.py
blobjugglerpy-0.0.0.dist-info/licenses/LICENSE
blobjugglerpy-0.0.0.dist-info/METADATA
blobjugglerpy-0.0.0.dist-info/WHEEL
blobjugglerpy-0.0.0.dist-info/entry_points.txt
blobjugglerpy-0.0.0.dist-info/top_level.txt
blobjugglerpy-0.0.0.dist-info/RECORD
