Metadata-Version: 2.4
Name: blobjugglerpy
Version: 0.0.0
Summary: Export ROS2 rosbag2 to CSV in PlotJuggler style or per-topic
Author-email: Emir Cem Gezer <emircem.gezer@gmail.com>
License:                     GNU GENERAL PUBLIC LICENSE
Project-URL: Homepage, https://github.com/incebellipipo/blobjugglerpy
Project-URL: Repository, https://github.com/incebellipipo/blobjugglerpy.git
Project-URL: Documentation, https://incebellipipo.github.io/blobjugglerpy/
Project-URL: Issues, https://github.com/incebellipipo/blobjugglerpy/issues
Project-URL: Source, https://github.com/incebellipipo/blobjugglerpy
Keywords: ROS2,rosbag2,CSV,PlotJuggler,robotics,logging
Classifier: Programming Language :: Python :: 3
Classifier: Programming Language :: Python :: 3 :: Only
Classifier: Programming Language :: Python :: 3.9
Classifier: Programming Language :: Python :: 3.10
Classifier: Programming Language :: Python :: 3.11
Classifier: Programming Language :: Python :: 3.12
Classifier: Programming Language :: Python :: 3.13
Classifier: License :: OSI Approved :: GNU General Public License v3 (GPLv3)
Classifier: Intended Audience :: Science/Research
Classifier: Topic :: Scientific/Engineering
Classifier: Operating System :: OS Independent
Requires-Python: >=3.9
License-File: LICENSE
Requires-Dist: PyYAML>=6.0
Dynamic: license-file
